odoo/addons/account_invoice_purchase_picking_selection/README.rst
odoo/addons/account_invoice_purchase_picking_selection/__init__.py
odoo/addons/account_invoice_purchase_picking_selection/__manifest__.py
odoo/addons/account_invoice_purchase_picking_selection/i18n/account_invoice_purchase_picking_selection.pot
odoo/addons/account_invoice_purchase_picking_selection/i18n/es.po
odoo/addons/account_invoice_purchase_picking_selection/models/__init__.py
odoo/addons/account_invoice_purchase_picking_selection/models/account_move.py
odoo/addons/account_invoice_purchase_picking_selection/models/stock_move.py
odoo/addons/account_invoice_purchase_picking_selection/models/stock_picking.py
odoo/addons/account_invoice_purchase_picking_selection/readme/CONTRIBUTORS.rst
odoo/addons/account_invoice_purchase_picking_selection/readme/DESCRIPTION.rst
odoo/addons/account_invoice_purchase_picking_selection/readme/USAGE.rst
odoo/addons/account_invoice_purchase_picking_selection/static/description/icon.png
odoo/addons/account_invoice_purchase_picking_selection/static/description/index.html
odoo/addons/account_invoice_purchase_picking_selection/tests/__init__.py
odoo/addons/account_invoice_purchase_picking_selection/tests/test_invoice_picking_selection.py
odoo/addons/account_invoice_purchase_picking_selection/views/account_move_views.xml
odoo14_addon_account_invoice_purchase_picking_selection-14.0.1.0.1.dist-info/METADATA
odoo14_addon_account_invoice_purchase_picking_selection-14.0.1.0.1.dist-info/WHEEL
odoo14_addon_account_invoice_purchase_picking_selection-14.0.1.0.1.dist-info/top_level.txt
odoo14_addon_account_invoice_purchase_picking_selection-14.0.1.0.1.dist-info/RECORD
